kinms/KinMS.py
kinms/KinMS2.py
kinms/KinMS_jax.py
kinms/__init__.py
kinms/radial_motion.py
kinms/examples/KinMS_testsuite.py
kinms/utils/KinMS_figures.py
kinms/utils/sauron_colormap.py
kinms-3.0.11.dist-info/LICENSE
kinms-3.0.11.dist-info/METADATA
kinms-3.0.11.dist-info/WHEEL
kinms-3.0.11.dist-info/top_level.txt
kinms-3.0.11.dist-info/RECORD
