Metadata-Version: 2.1
Name: kinms
Version: 3.0.11
Summary: The KinMS (KINematic Molecular Simulation) package can be used to simulate observations of arbitary molecular/atomic cold gas distributions.
Home-page: https://github.com/TimothyADavis/KinMSpy
Author: Timothy A. Davis
Author-email: DavisT@cardiff.ac.uk
License: MIT
Classifier: Development Status :: 4 - Beta
Classifier: License :: OSI Approved :: MIT License
Classifier: Programming Language :: Python :: 3
Classifier: Operating System :: OS Independent
License-File: LICENSE
Requires-Dist: numpy
Requires-Dist: matplotlib
Requires-Dist: scipy
Requires-Dist: astropy
